README.rst
setup.py
b2g_util/__init__.py
b2g_util/backup_restore_profile.py
b2g_util/check_versions.py
b2g_util/enable_certapps_devtools.py
b2g_util/flash_taskcluster.py
b2g_util/get_crashreports.py
b2g_util/quick_flash.py
b2g_util/reset_phone.py
b2g_util/shallow_flash.py
b2g_util.egg-info/PKG-INFO
b2g_util.egg-info/SOURCES.txt
b2g_util.egg-info/dependency_links.txt
b2g_util.egg-info/entry_points.txt
b2g_util.egg-info/not-zip-safe
b2g_util.egg-info/requires.txt
b2g_util.egg-info/top_level.txt
b2g_util/misc/__init__.py
b2g_util/misc/optimizejars.py
b2g_util/util/__init__.py
b2g_util/util/adb_helper.py
b2g_util/util/b2g_helper.py
b2g_util/util/console_dialog.py
b2g_util/util/console_utilities.py
b2g_util/util/decompressor.py
b2g_util/util/downloader.py