Metadata-Version: 1.0
Name: b2g-util
Version: 0.0.16
Summary: B2G Utilities
Home-page: https://github.com/askeing/b2g-util-python
Author: Askeing Yen
Author-email: askeing@gmail.com
License: UNKNOWN
Keywords: mozilla b2g firefoxos fxos firefox utilities
Platform: UNKNOWN
